sumstats/__init__.py
sumstats/sumstats.py
sumstats-0.1.2.dist-info/LICENSE
sumstats-0.1.2.dist-info/METADATA
sumstats-0.1.2.dist-info/WHEEL
sumstats-0.1.2.dist-info/top_level.txt
sumstats-0.1.2.dist-info/RECORD
