Metadata-Version: 2.1
Name: sumstats
Version: 0.1.2
Summary: utilities for working with GWAS summary statistics
Home-page: https://gitlab.com/salk-tm/sumstats
Author: Anthony Aylward
Author-email: aaylward@salk.edu
License: UNKNOWN
Platform: UNKNOWN
Classifier: Programming Language :: Python :: 3
Classifier: License :: OSI Approved :: MIT License
Classifier: Operating System :: OS Independent
License-File: LICENSE
Requires-Dist: scipy
